{
  "date": "2026-04-07",
  "summary": {
    "total": 40,
    "healthy": 37,
    "errors": 0,
    "warnings": 3,
    "new": 0,
    "fixed": 0,
    "healthScore": 98
  },
  "pages": [
    {
      "url": "https://www.growthikmedia.com/",
      "status": 200,
      "responseTime": 367,
      "title": "Best Digital Marketing Agency in Pune | Growthik Media",
      "metaDesc": "Growthik Media is a leading digital marketing agency in Pune offering SEO, Google Ads and AI-driven growth strategies to scale your business and maximize ROI.",
      "h1": "BestDigital Marketing Agencyin Pune for ROI-Driven Growth",
      "canonical": "https://www.growthikmedia.com/",
      "wordCount": 1819,
      "links": 89,
      "missingAlt": 0,
      "noindex": false,
      "errors": [],
      "warnings": []
    },
    {
      "url": "https://www.growthikmedia.com/about/",
      "status": 200,
      "responseTime": 1028,
      "title": "About Top Digital Marketing Agency | Growthik Media",
      "metaDesc": "Growthik Media is an AI-powered growth engineering company that builds predictable revenue systems - not just marketing campaigns. We help ambitious brands scale with ROI-driven performance engineering.",
      "h1": "GROWTHIK MEDIAAI-Driven Digital Marketing & SEO Services in Pune",
      "canonical": "https://www.growthikmedia.com/about/",
      "wordCount": 1499,
      "links": 45,
      "missingAlt": 0,
      "noindex": false,
      "errors": [],
      "warnings": [
        "Meta description too long (>165 chars)"
      ]
    },
    {
      "url": "https://www.growthikmedia.com/contact/",
      "status": 200,
      "responseTime": 1386,
      "title": "Contact Us | Growthik Media - Get in Touch",
      "metaDesc": "Get in touch with Growthik Media for professional video production, content creation and digital marketing services. We're here to help bring your vision to life.",
      "h1": "Let’s Grow Your BusinessDigitally.",
      "canonical": "https://www.growthikmedia.com/contact/",
      "wordCount": 654,
      "links": 46,
      "missingAlt": 0,
      "noindex": false,
      "errors": [],
      "warnings": []
    },
    {
      "url": "https://www.growthikmedia.com/audit/",
      "status": 200,
      "responseTime": 786,
      "title": "Free SEO & Growth Audit Pune | Growthik Media",
      "metaDesc": "Get a professional digital marketing and SEO audit for your Pune-based business. Data-driven strategy to scale your brand and maximize ROI.",
      "h1": "Stop Guessing. Start Scaling.",
      "canonical": "https://www.growthikmedia.com/audit/",
      "wordCount": 781,
      "links": 33,
      "missingAlt": 0,
      "noindex": false,
      "errors": [],
      "warnings": []
    },
    {
      "url": "https://www.growthikmedia.com/portfolio/",
      "status": 200,
      "responseTime": 758,
      "title": "Our Work | 30+ Tech & Marketing Projects | Growthik Media",
      "metaDesc": "Explore our comprehensive portfolio of 30+ web development projects, marketing campaigns, healthcare platforms and real estate solutions across Pune and Dubai.",
      "h1": "Ideas Built into  Real-World Impact.",
      "canonical": "",
      "wordCount": 3836,
      "links": 54,
      "missingAlt": 0,
      "noindex": false,
      "errors": [],
      "warnings": []
    },
    {
      "url": "https://www.growthikmedia.com/portfolio/case-studies/",
      "status": 200,
      "responseTime": 811,
      "title": "In-Depth Case Studies | Growthik Media",
      "metaDesc": "A deep dive into how we constructed robust software solutions and scaled digital agencies.",
      "h1": "See The Deep Method.",
      "canonical": "",
      "wordCount": 1826,
      "links": 42,
      "missingAlt": 0,
      "noindex": false,
      "errors": [],
      "warnings": []
    },
    {
      "url": "https://www.growthikmedia.com/services/seo/",
      "status": 200,
      "responseTime": 710,
      "title": "SEO Company in Pune | Growthik Media",
      "metaDesc": "Top-rated SEO company in Pune. Rank on Page 1 of Google with our data-driven SEO strategies. Get a free SEO audit today.",
      "h1": "Top Agency For SEO Company in Pune",
      "canonical": "https://www.growthikmedia.com/services/seo/",
      "wordCount": 999,
      "links": 34,
      "missingAlt": 0,
      "noindex": false,
      "errors": [],
      "warnings": []
    },
    {
      "url": "https://www.growthikmedia.com/services/ppc-google-ads/",
      "status": 200,
      "responseTime": 738,
      "title": "Google Ads Agency in Pune | High ROI PPC | Growthik Media",
      "metaDesc": "Certified Google Ads agency in Pune. Managing high-converting PPC campaigns with lower CPC and maximum ROI. Free audit.",
      "h1": "Top Agency For Google Ads Agency in Pune",
      "canonical": "https://www.growthikmedia.com/services/ppc-google-ads/",
      "wordCount": 842,
      "links": 34,
      "missingAlt": 0,
      "noindex": false,
      "errors": [],
      "warnings": []
    },
    {
      "url": "https://www.growthikmedia.com/services/social-media-marketing/",
      "status": 200,
      "responseTime": 805,
      "title": "Social Media Marketing Agency in Pune | Growthik Media",
      "metaDesc": "Leading social media marketing in Pune. Instagram, LinkedIn & Facebook marketing that builds community and drives sales.",
      "h1": "Top Agency For Social Media Marketing Agency in Pune",
      "canonical": "https://www.growthikmedia.com/services/social-media-marketing/",
      "wordCount": 835,
      "links": 34,
      "missingAlt": 0,
      "noindex": false,
      "errors": [],
      "warnings": []
    },
    {
      "url": "https://www.growthikmedia.com/services/website-development/",
      "status": 200,
      "responseTime": 739,
      "title": "Website Development Company in Pune | Next.js | Growthik Media",
      "metaDesc": "Top website development company in Pune. Building fast, SEO-optimized websites using Next.js and modern web technologies.",
      "h1": "Top Agency For Website Development Company in Pune",
      "canonical": "https://www.growthikmedia.com/services/website-development/",
      "wordCount": 828,
      "links": 34,
      "missingAlt": 0,
      "noindex": false,
      "errors": [],
      "warnings": []
    },
    {
      "url": "https://www.growthikmedia.com/services/website-development/nextjs/",
      "status": 200,
      "responseTime": 672,
      "title": "Next.js Development Services in Pune | Growthik Media",
      "metaDesc": "Looking for a professional Next.js Development company in Pune? We provide custom, SEO-optimized, Next.js Development services for businesses. Call Now!",
      "h1": "Best Next.js Development Services in Pune – Custom, SEO-Friendly & Conversion-Focused",
      "canonical": "https://www.growthikmedia.com/services/website-development/nextjs/",
      "wordCount": 3486,
      "links": 43,
      "missingAlt": 0,
      "noindex": false,
      "errors": [],
      "warnings": []
    },
    {
      "url": "https://www.growthikmedia.com/services/website-development/react/",
      "status": 200,
      "responseTime": 681,
      "title": "React Development Services in Pune | Growthik Media",
      "metaDesc": "Looking for a professional React Development company in Pune? We provide custom, SEO-optimized, React Development services for businesses. Call Now!",
      "h1": "Best React Development Services in Pune – Custom, SEO-Friendly & Conversion-Focused",
      "canonical": "https://www.growthikmedia.com/services/website-development/react/",
      "wordCount": 3486,
      "links": 43,
      "missingAlt": 0,
      "noindex": false,
      "errors": [],
      "warnings": []
    },
    {
      "url": "https://www.growthikmedia.com/services/website-development/full-stack/",
      "status": 200,
      "responseTime": 801,
      "title": "Full Stack Web Development in Pune | Growthik Media",
      "metaDesc": "Looking for a professional Full-Stack Solutions company in Pune? We provide custom, SEO-optimized, Full-Stack Solutions services for businesses. Call Now!",
      "h1": "Best Full-Stack Solutions Services in Pune – Custom, SEO-Friendly & Conversion-Focused",
      "canonical": "https://www.growthikmedia.com/services/website-development/full-stack/",
      "wordCount": 3487,
      "links": 43,
      "missingAlt": 0,
      "noindex": false,
      "errors": [],
      "warnings": []
    },
    {
      "url": "https://www.growthikmedia.com/services/ecommerce-development/",
      "status": 200,
      "responseTime": 774,
      "title": "eCommerce Website Development Agency in Pune | Growthik Media",
      "metaDesc": "Professional eCommerce development in Pune. Scaling online stores with Razorpay, inventory management and high-converting UX.",
      "h1": "Top Agency For eCommerce Development Agency in Pune",
      "canonical": "https://www.growthikmedia.com/services/ecommerce-development/",
      "wordCount": 832,
      "links": 34,
      "missingAlt": 0,
      "noindex": false,
      "errors": [],
      "warnings": []
    },
    {
      "url": "https://www.growthikmedia.com/services/website-design-company-pune/",
      "status": 200,
      "responseTime": 838,
      "title": "Best Website Design Company in Pune | Growthik Media",
      "metaDesc": "Looking for a professional website design company in Pune? We provide custom, SEO-optimized, mobile-responsive website development services for businesses. Call Now!",
      "h1": "Best Website Design Pune",
      "canonical": "https://www.growthikmedia.com/services/website-design-company-pune/",
      "wordCount": 5161,
      "links": 52,
      "missingAlt": 0,
      "noindex": false,
      "errors": [],
      "warnings": []
    },
    {
      "url": "https://www.growthikmedia.com/services/branding-consulting/",
      "status": 200,
      "responseTime": 916,
      "title": "Brand Consulting Agency in Pune | Growthik Media",
      "metaDesc": "Expert branding consulting for Pune businesses. Brand audits, rebranding strategy and actionable brand growth roadmaps.",
      "h1": "Top Agency For Brand Consulting Agency in Pune",
      "canonical": "https://www.growthikmedia.com/services/branding-consulting/",
      "wordCount": 818,
      "links": 34,
      "missingAlt": 0,
      "noindex": false,
      "errors": [],
      "warnings": []
    },
    {
      "url": "https://www.growthikmedia.com/services/brand-identity/",
      "status": 200,
      "responseTime": 695,
      "title": "Brand Identity Design Agency in Pune | Growthik Media",
      "metaDesc": "Professional brand identity design in Pune. Logo, colour palette, typography & brand guidelines for startups and SMEs.",
      "h1": "Top Agency For Brand Identity Design Agency in Pune",
      "canonical": "https://www.growthikmedia.com/services/brand-identity/",
      "wordCount": 954,
      "links": 34,
      "missingAlt": 0,
      "noindex": false,
      "errors": [],
      "warnings": []
    },
    {
      "url": "https://www.growthikmedia.com/services/brand-strategy/",
      "status": 200,
      "responseTime": 725,
      "title": "Brand Strategy Agency in Pune | Growthik Media",
      "metaDesc": "Expert brand strategy for Pune businesses. Positioning, competitive analysis, messaging framework and go-to-market planning.",
      "h1": "Top Agency For Brand Strategy Agency in Pune",
      "canonical": "https://www.growthikmedia.com/services/brand-strategy/",
      "wordCount": 812,
      "links": 34,
      "missingAlt": 0,
      "noindex": false,
      "errors": [],
      "warnings": []
    },
    {
      "url": "https://www.growthikmedia.com/services/brand-name/",
      "status": 200,
      "responseTime": 705,
      "title": "Brand Naming Agency in Pune | Creative Brand Names | Growthik Media",
      "metaDesc": "Creative brand naming in Pune. Unique, memorable brand names for startups and products. Trademark-friendly naming.",
      "h1": "Top Agency For Brand Naming Agency in Pune",
      "canonical": "https://www.growthikmedia.com/services/brand-name/",
      "wordCount": 836,
      "links": 34,
      "missingAlt": 0,
      "noindex": false,
      "errors": [],
      "warnings": []
    },
    {
      "url": "https://www.growthikmedia.com/services/branding-design/",
      "status": 200,
      "responseTime": 660,
      "title": "Branding Design Agency in Pune | Growthik Media",
      "metaDesc": "Complete branding design in Pune. Visual identity, brand collateral and design systems for modern businesses.",
      "h1": "Top Agency For Branding Design Agency in Pune",
      "canonical": "https://www.growthikmedia.com/services/branding-design/",
      "wordCount": 818,
      "links": 34,
      "missingAlt": 0,
      "noindex": false,
      "errors": [],
      "warnings": []
    },
    {
      "url": "https://www.growthikmedia.com/services/brand-marketing-communications/",
      "status": 200,
      "responseTime": 755,
      "title": "Brand Marketing & Communications Agency Pune | Growthik Media",
      "metaDesc": "Strategic brand marketing and communications in Pune. Messaging frameworks, PR campaigns and brand voice development.",
      "h1": "Top Agency For Brand Marketing & Communications in Pune",
      "canonical": "https://www.growthikmedia.com/services/brand-marketing-communications/",
      "wordCount": 836,
      "links": 34,
      "missingAlt": 0,
      "noindex": false,
      "errors": [],
      "warnings": []
    },
    {
      "url": "https://www.growthikmedia.com/services/content-marketing/",
      "status": 200,
      "responseTime": 772,
      "title": "Content Marketing Agency in Pune | Growthik Media",
      "metaDesc": "Strategic content marketing in Pune. Blog writing, whitepapers, case studies and content distribution that drives B2B leads.",
      "h1": "Top Agency For Content Marketing Agency in Pune",
      "canonical": "https://www.growthikmedia.com/services/content-marketing/",
      "wordCount": 818,
      "links": 34,
      "missingAlt": 0,
      "noindex": false,
      "errors": [],
      "warnings": []
    },
    {
      "url": "https://www.growthikmedia.com/services/performance-marketing/",
      "status": 200,
      "responseTime": 651,
      "title": "Performance Marketing Agency in Pune | Growthik Media",
      "metaDesc": "Data-driven performance marketing for Pune businesses. Result-oriented campaigns for ROAS, CPA and revenue growth.",
      "h1": "Performance Marketing Agency in Pune",
      "canonical": "https://www.growthikmedia.com/services/performance-marketing/",
      "wordCount": 919,
      "links": 34,
      "missingAlt": 0,
      "noindex": false,
      "errors": [],
      "warnings": []
    },
    {
      "url": "https://www.growthikmedia.com/services/meta-ads/",
      "status": 200,
      "responseTime": 726,
      "title": "Meta Ads Agency in Pune | Facebook & Instagram Ads | Growthik Media",
      "metaDesc": "Performance Meta Ads management in Pune. Facebook & Instagram campaigns for leads, sales and brand awareness.",
      "h1": "Meta Ads Agency in Pune",
      "canonical": "https://www.growthikmedia.com/services/meta-ads/",
      "wordCount": 931,
      "links": 34,
      "missingAlt": 0,
      "noindex": false,
      "errors": [],
      "warnings": []
    },
    {
      "url": "https://www.growthikmedia.com/services/email-marketing/",
      "status": 200,
      "responseTime": 711,
      "title": "Email Marketing Agency in Pune | Growthik Media",
      "metaDesc": "High-ROI email marketing campaigns for Pune businesses. Newsletters, drip sequences, automation and list management.",
      "h1": "Email Marketing Agency in Pune",
      "canonical": "https://www.growthikmedia.com/services/email-marketing/",
      "wordCount": 917,
      "links": 34,
      "missingAlt": 0,
      "noindex": false,
      "errors": [],
      "warnings": []
    },
    {
      "url": "https://www.growthikmedia.com/services/whatsapp-marketing/",
      "status": 200,
      "responseTime": 795,
      "title": "Top WhatsApp Marketing Services Pune | Growthik Media",
      "metaDesc": "Boost sales with top WhatsApp marketing services in Pune. Growthik Media offers official WhatsApp Business API integration and bulk messaging for high ROI.",
      "h1": "Top WhatsApp Marketing Services Pune",
      "canonical": "https://www.growthikmedia.com/services/whatsapp-marketing/",
      "wordCount": 1470,
      "links": 35,
      "missingAlt": 0,
      "noindex": false,
      "errors": [],
      "warnings": []
    },
    {
      "url": "https://www.growthikmedia.com/services/sms-marketing/",
      "status": 200,
      "responseTime": 732,
      "title": "Bulk SMS Marketing Services in Pune | Growthik Media",
      "metaDesc": "Scale your business with the best bulk SMS marketing services in Pune. Growthik Media delivers high-ROI promotional and transactional SMS campaigns that convert.",
      "h1": "Bulk SMS Marketing Services in Pune",
      "canonical": "https://www.growthikmedia.com/services/sms-marketing/",
      "wordCount": 1598,
      "links": 35,
      "missingAlt": 0,
      "noindex": false,
      "errors": [],
      "warnings": []
    },
    {
      "url": "https://www.growthikmedia.com/services/lead-generation/",
      "status": 200,
      "responseTime": 692,
      "title": "Lead Generation Agency in Pune | Growthik Media",
      "metaDesc": "Qualified lead generation for Pune businesses. Multi-channel campaigns across Google, Meta, LinkedIn and email.",
      "h1": "Lead Generation Agency in Pune",
      "canonical": "https://www.growthikmedia.com/services/lead-generation/",
      "wordCount": 925,
      "links": 34,
      "missingAlt": 0,
      "noindex": false,
      "errors": [],
      "warnings": []
    },
    {
      "url": "https://www.growthikmedia.com/services/influencer-management/",
      "status": 200,
      "responseTime": 894,
      "title": "Influencer Management Agency Pune | Growthik Media",
      "metaDesc": "Scale your brand with the top influencer management agency in Pune. We connect you with authentic influencers to drive engagement and sales.",
      "h1": "Influencer Management Agency Pune",
      "canonical": "https://www.growthikmedia.com/services/influencer-management/",
      "wordCount": 1380,
      "links": 35,
      "missingAlt": 0,
      "noindex": false,
      "errors": [],
      "warnings": []
    },
    {
      "url": "https://www.growthikmedia.com/services/media-planning-buying/",
      "status": 200,
      "responseTime": 711,
      "title": "Expert Media Planning and Buying Pune | Growthik Media",
      "metaDesc": "Maximize your ad spend with expert media planning and buying in Pune. Our data-driven digital media strategy ensures your brand reaches the right audience.",
      "h1": "Expert Media Planning and Buying Pune",
      "canonical": "https://www.growthikmedia.com/services/media-planning-buying/",
      "wordCount": 1430,
      "links": 35,
      "missingAlt": 0,
      "noindex": false,
      "errors": [],
      "warnings": []
    },
    {
      "url": "https://www.growthikmedia.com/services/political-digital-marketing/",
      "status": 200,
      "responseTime": 681,
      "title": "Top Political Digital Marketing Pune | Growthik Media",
      "metaDesc": "Win elections with the top political digital marketing agency in Pune. Professional social media management, sentiment analysis and voter outreach strategies.",
      "h1": "Top Political Digital Marketing Pune",
      "canonical": "https://www.growthikmedia.com/services/political-digital-marketing/",
      "wordCount": 1299,
      "links": 35,
      "missingAlt": 0,
      "noindex": false,
      "errors": [],
      "warnings": []
    },
    {
      "url": "https://www.growthikmedia.com/services/youtube-seo/",
      "status": 200,
      "responseTime": 1516,
      "title": "YouTube Video SEO Services in Pune | Growthik Media",
      "metaDesc": "Dominate video search with expert YouTube Video SEO services in Pune. Growthik Media helps you rank higher, increase views and grow your channel content.",
      "h1": "YouTube Video SEO Services in Pune",
      "canonical": "https://www.growthikmedia.com/services/youtube-seo/",
      "wordCount": 1595,
      "links": 38,
      "missingAlt": 0,
      "noindex": false,
      "errors": [],
      "warnings": []
    },
    {
      "url": "https://www.growthikmedia.com/services/web-application/",
      "status": 200,
      "responseTime": 730,
      "title": "Custom Web App Development in Pune | Growthik Media",
      "metaDesc": "Looking for a professional web application company in Pune? We provide custom, SEO-optimized, mobile-responsive website development services for businesses. Call Now!",
      "h1": "Best Website Design Pune",
      "canonical": "https://www.growthikmedia.com/services/web-application/",
      "wordCount": 5028,
      "links": 52,
      "missingAlt": 0,
      "noindex": false,
      "errors": [],
      "warnings": [
        "Meta description too long (>165 chars)"
      ]
    },
    {
      "url": "https://www.growthikmedia.com/services/website-maintenance/",
      "status": 200,
      "responseTime": 827,
      "title": "Website Maintenance Services Pune | Growthik Media",
      "metaDesc": "Looking for a professional website maintenance company in Pune? We provide custom, SEO-optimized, mobile-responsive website development services for businesses. Call Now!",
      "h1": "Best Website Design Pune",
      "canonical": "https://www.growthikmedia.com/services/website-maintenance/",
      "wordCount": 5026,
      "links": 52,
      "missingAlt": 0,
      "noindex": false,
      "errors": [],
      "warnings": [
        "Meta description too long (>165 chars)"
      ]
    },
    {
      "url": "https://www.growthikmedia.com/services/logo-design/",
      "status": 200,
      "responseTime": 809,
      "title": "Logo Design Agency in Pune | Growthik Media",
      "metaDesc": "Creative logo design agency in Pune. Unique, memorable logos for startups, SMEs and enterprises. Multiple revisions included.",
      "h1": "Top Agency For Logo Design Agency in Pune",
      "canonical": "https://www.growthikmedia.com/services/logo-design/",
      "wordCount": 828,
      "links": 34,
      "missingAlt": 0,
      "noindex": false,
      "errors": [],
      "warnings": []
    },
    {
      "url": "https://www.growthikmedia.com/services/brochure-design/",
      "status": 200,
      "responseTime": 625,
      "title": "Brochure Design Company in Pune | Growthik Media",
      "metaDesc": "Professional brochure design in Pune. Company profiles, product brochures, flyers and all print collateral.",
      "h1": "Top Agency For Brochure Design Company in Pune",
      "canonical": "https://www.growthikmedia.com/services/brochure-design/",
      "wordCount": 816,
      "links": 34,
      "missingAlt": 0,
      "noindex": false,
      "errors": [],
      "warnings": []
    },
    {
      "url": "https://www.growthikmedia.com/services/business-card-design/",
      "status": 200,
      "responseTime": 975,
      "title": "Business Card Design Company Pune | Growthik Media",
      "metaDesc": "Make a powerful first impression with the best business card design in Pune. Premium, professional visiting card designs that reflect your brand identity.",
      "h1": "Business Card Design Company Pune",
      "canonical": "https://www.growthikmedia.com/services/business-card-design/",
      "wordCount": 1483,
      "links": 35,
      "missingAlt": 0,
      "noindex": false,
      "errors": [],
      "warnings": []
    },
    {
      "url": "https://www.growthikmedia.com/services/letterhead-design/",
      "status": 200,
      "responseTime": 841,
      "title": "Professional Letterhead Design Pune | Growthik Media",
      "metaDesc": "Establish corporate authority with professional letterhead design in Pune. Custom corporate stationery and digital letterhead templates for your brand.",
      "h1": "Professional Letterhead Design Pune",
      "canonical": "https://www.growthikmedia.com/services/letterhead-design/",
      "wordCount": 1476,
      "links": 35,
      "missingAlt": 0,
      "noindex": false,
      "errors": [],
      "warnings": []
    },
    {
      "url": "https://www.growthikmedia.com/services/social-media-promotions/",
      "status": 200,
      "responseTime": 1183,
      "title": "Social Media Promotions Agency in Pune | Growthik Media",
      "metaDesc": "Boost your reach with social media promotions in Pune. Targeted ad campaigns and viral marketing for businesses of all sizes.",
      "h1": "Social Media Promotions in Pune",
      "canonical": "https://www.growthikmedia.com/services/social-media-promotions/",
      "wordCount": 936,
      "links": 34,
      "missingAlt": 0,
      "noindex": false,
      "errors": [],
      "warnings": []
    },
    {
      "url": "https://www.growthikmedia.com/blog/",
      "status": 200,
      "responseTime": 2246,
      "title": "Digital Marketing & SEO Blog Pune | Growthik Media",
      "metaDesc": "Expert articles on SEO, web design, Google Ads and digital marketing strategies tailored for Pune businesses. Written by the Growthik Media team.",
      "h1": "Master the Art of Digital Growth",
      "canonical": "https://www.growthikmedia.com/blog/",
      "wordCount": 749,
      "links": 41,
      "missingAlt": 0,
      "noindex": false,
      "errors": [],
      "warnings": []
    }
  ],
  "trend": [
    98,
    98
  ]
}